{
  "id": "S1|Ösophaguskarzinom Fr Gerhild mit Dr Hatice 18.06.25.m4a",
  "name": "Ösophaguskarzinom Fr Gerhild mit Dr Hatice 18.06.25.m4a",
  "title": "Ösophaguskarzinom Fr Gerhild mit Dr Hatice 18.06.25.m4a",
  "src": "S1",
  "url": "https://archive.org/download/vorhofflimmern-bei-bekannter-khk-dr-oemer-dr-remzi-09.05.25/O%CC%88sophaguskarzinom%20Fr%20Gerhild%20mit%20Dr%20Hatice%2018.06.25.m4a",
  "duration": 2167.787,
  "sample_rate": 16000,
  "threshold": 0.015,
  "frame_ms": 20,
  "min_silence_ms": 900,
  "merge_gap_ms": 180,
  "keep_lead_ms": 60,
  "keep_tail_ms": 80,
  "min_skip_ms": 350,
  "max_skip_ms": 15000,
  "algo_version": "sm-v1",
  "analyzed_at": "2026-04-17T19:45:25Z",
  "segments": [
    {
      "start": 0.06,
      "end": 2.22
    },
    {
      "start": 18.18,
      "end": 20.62
    },
    {
      "start": 27.52,
      "end": 28.38
    },
    {
      "start": 37.88,
      "end": 40.22
    },
    {
      "start": 49.56,
      "end": 50.56
    },
    {
      "start": 55.28,
      "end": 56.46
    },
    {
      "start": 63.34,
      "end": 64.54
    },
    {
      "start": 68.34,
      "end": 69.14
    },
    {
      "start": 73.46,
      "end": 74.36
    },
    {
      "start": 79.28,
      "end": 84.08
    },
    {
      "start": 86.36,
      "end": 87.32
    },
    {
      "start": 88.64,
      "end": 92.86
    },
    {
      "start": 103.5,
      "end": 104.44
    },
    {
      "start": 125.92,
      "end": 127.1
    },
    {
      "start": 163.88,
      "end": 165.32
    },
    {
      "start": 168.02,
      "end": 169.36
    },
    {
      "start": 170.94,
      "end": 171.82
    },
    {
      "start": 172.3,
      "end": 173.14
    },
    {
      "start": 182.78,
      "end": 185.0
    },
    {
      "start": 190.54,
      "end": 191.92
    },
    {
      "start": 206.98,
      "end": 208.4
    },
    {
      "start": 209.04,
      "end": 209.82
    },
    {
      "start": 237.76,
      "end": 238.92
    },
    {
      "start": 241.16,
      "end": 242.02
    },
    {
      "start": 250.84,
      "end": 251.72
    },
    {
      "start": 252.64,
      "end": 254.08
    },
    {
      "start": 260.74,
      "end": 262.92
    },
    {
      "start": 267.52,
      "end": 269.16
    },
    {
      "start": 272.5,
      "end": 275.8
    },
    {
      "start": 295.66,
      "end": 299.8
    },
    {
      "start": 303.26,
      "end": 304.96
    },
    {
      "start": 310.14,
      "end": 310.96
    },
    {
      "start": 312.98,
      "end": 313.8
    },
    {
      "start": 315.9,
      "end": 317.14
    },
    {
      "start": 318.78,
      "end": 319.86
    },
    {
      "start": 332.06,
      "end": 333.16
    },
    {
      "start": 373.86,
      "end": 375.52
    },
    {
      "start": 393.86,
      "end": 394.92
    },
    {
      "start": 398.22,
      "end": 400.7
    },
    {
      "start": 405.3,
      "end": 406.46
    },
    {
      "start": 409.52,
      "end": 410.32
    },
    {
      "start": 414.52,
      "end": 416.74
    },
    {
      "start": 421.12,
      "end": 422.04
    },
    {
      "start": 424.04,
      "end": 424.92
    },
    {
      "start": 426.78,
      "end": 428.6
    },
    {
      "start": 432.82,
      "end": 434.3
    },
    {
      "start": 436.08,
      "end": 437.44
    },
    {
      "start": 442.2,
      "end": 442.96
    },
    {
      "start": 450.34,
      "end": 451.38
    },
    {
      "start": 455.44,
      "end": 456.46
    },
    {
      "start": 459.08,
      "end": 460.08
    },
    {
      "start": 464.14,
      "end": 465.5
    },
    {
      "start": 470.22,
      "end": 471.06
    },
    {
      "start": 472.54,
      "end": 475.64
    },
    {
      "start": 477.74,
      "end": 479.12
    },
    {
      "start": 480.86,
      "end": 482.38
    },
    {
      "start": 484.78,
      "end": 485.88
    },
    {
      "start": 490.14,
      "end": 496.22
    },
    {
      "start": 498.46,
      "end": 499.42
    },
    {
      "start": 502.9,
      "end": 504.2
    },
    {
      "start": 510.6,
      "end": 511.4
    },
    {
      "start": 519.04,
      "end": 520.88
    },
    {
      "start": 529.14,
      "end": 530.42
    },
    {
      "start": 536.62,
      "end": 537.52
    },
    {
      "start": 541.2,
      "end": 542.74
    },
    {
      "start": 548.5,
      "end": 549.8
    },
    {
      "start": 555.38,
      "end": 556.36
    },
    {
      "start": 562.02,
      "end": 565.84
    },
    {
      "start": 566.7,
      "end": 567.94
    },
    {
      "start": 568.26,
      "end": 569.74
    },
    {
      "start": 572.34,
      "end": 573.58
    },
    {
      "start": 574.6,
      "end": 575.42
    },
    {
      "start": 583.34,
      "end": 584.9
    },
    {
      "start": 586.34,
      "end": 587.76
    },
    {
      "start": 590.06,
      "end": 590.9
    },
    {
      "start": 595.16,
      "end": 595.96
    },
    {
      "start": 606.12,
      "end": 606.94
    },
    {
      "start": 610.42,
      "end": 611.46
    },
    {
      "start": 613.42,
      "end": 615.2
    },
    {
      "start": 627.14,
      "end": 628.44
    },
    {
      "start": 634.78,
      "end": 635.84
    },
    {
      "start": 641.26,
      "end": 642.16
    },
    {
      "start": 647.48,
      "end": 649.36
    },
    {
      "start": 662.24,
      "end": 664.18
    },
    {
      "start": 665.28,
      "end": 666.08
    },
    {
      "start": 668.04,
      "end": 670.38
    },
    {
      "start": 677.02,
      "end": 679.92
    },
    {
      "start": 682.86,
      "end": 684.22
    },
    {
      "start": 687.96,
      "end": 691.06
    },
    {
      "start": 698.34,
      "end": 699.34
    },
    {
      "start": 705.08,
      "end": 706.3
    },
    {
      "start": 711.6,
      "end": 713.2
    },
    {
      "start": 728.06,
      "end": 729.98
    },
    {
      "start": 737.68,
      "end": 738.48
    },
    {
      "start": 739.9,
      "end": 740.78
    },
    {
      "start": 751.66,
      "end": 754.86
    },
    {
      "start": 756.56,
      "end": 757.9
    },
    {
      "start": 761.84,
      "end": 762.72
    },
    {
      "start": 765.54,
      "end": 766.54
    },
    {
      "start": 769.98,
      "end": 772.14
    },
    {
      "start": 773.44,
      "end": 774.62
    },
    {
      "start": 775.56,
      "end": 776.84
    },
    {
      "start": 782.18,
      "end": 783.1
    },
    {
      "start": 787.16,
      "end": 791.86
    },
    {
      "start": 794.14,
      "end": 796.02
    },
    {
      "start": 796.74,
      "end": 797.7
    },
    {
      "start": 818.64,
      "end": 819.62
    },
    {
      "start": 822.9,
      "end": 825.58
    },
    {
      "start": 831.54,
      "end": 834.06
    },
    {
      "start": 839.28,
      "end": 840.28
    },
    {
      "start": 841.74,
      "end": 842.62
    },
    {
      "start": 846.16,
      "end": 847.16
    },
    {
      "start": 848.58,
      "end": 849.76
    },
    {
      "start": 862.98,
      "end": 865.78
    },
    {
      "start": 867.92,
      "end": 868.96
    },
    {
      "start": 873.7,
      "end": 875.62
    },
    {
      "start": 884.38,
      "end": 886.52
    },
    {
      "start": 887.22,
      "end": 889.08
    },
    {
      "start": 890.42,
      "end": 891.26
    },
    {
      "start": 892.24,
      "end": 897.7
    },
    {
      "start": 899.66,
      "end": 901.08
    },
    {
      "start": 901.9,
      "end": 903.24
    },
    {
      "start": 911.5,
      "end": 912.44
    },
    {
      "start": 915.94,
      "end": 916.78
    },
    {
      "start": 919.32,
      "end": 920.22
    },
    {
      "start": 926.92,
      "end": 927.8
    },
    {
      "start": 930.38,
      "end": 931.24
    },
    {
      "start": 932.06,
      "end": 933.04
    },
    {
      "start": 949.52,
      "end": 950.68
    },
    {
      "start": 951.08,
      "end": 951.92
    },
    {
      "start": 960.86,
      "end": 962.9
    },
    {
      "start": 969.4,
      "end": 970.18
    },
    {
      "start": 971.74,
      "end": 972.76
    },
    {
      "start": 981.56,
      "end": 986.34
    },
    {
      "start": 993.98,
      "end": 995.12
    },
    {
      "start": 996.62,
      "end": 998.02
    },
    {
      "start": 1002.72,
      "end": 1003.6
    },
    {
      "start": 1017.74,
      "end": 1019.44
    },
    {
      "start": 1061.06,
      "end": 1061.94
    },
    {
      "start": 1067.88,
      "end": 1068.68
    },
    {
      "start": 1073.34,
      "end": 1082.46
    },
    {
      "start": 1084.34,
      "end": 1085.54
    },
    {
      "start": 1091.12,
      "end": 1093.2
    },
    {
      "start": 1109.06,
      "end": 1116.04
    },
    {
      "start": 1117.84,
      "end": 1132.84
    },
    {
      "start": 1135.28,
      "end": 1136.26
    },
    {
      "start": 1137.6,
      "end": 1138.5
    },
    {
      "start": 1145.76,
      "end": 1146.62
    },
    {
      "start": 1166.24,
      "end": 1167.68
    },
    {
      "start": 1221.1,
      "end": 1221.86
    },
    {
      "start": 1236.68,
      "end": 1237.76
    },
    {
      "start": 1291.98,
      "end": 1292.88
    },
    {
      "start": 1295.76,
      "end": 1297.04
    },
    {
      "start": 1336.94,
      "end": 1338.16
    },
    {
      "start": 1347.22,
      "end": 1348.96
    },
    {
      "start": 1370.4,
      "end": 1372.64
    },
    {
      "start": 1387.2,
      "end": 1388.28
    },
    {
      "start": 1404.84,
      "end": 1406.08
    },
    {
      "start": 1407.26,
      "end": 1408.44
    },
    {
      "start": 1423.48,
      "end": 1425.18
    },
    {
      "start": 1426.38,
      "end": 1427.34
    },
    {
      "start": 1430.52,
      "end": 1432.68
    },
    {
      "start": 1433.8,
      "end": 1436.26
    },
    {
      "start": 1490.94,
      "end": 1493.02
    },
    {
      "start": 1498.4,
      "end": 1499.24
    },
    {
      "start": 1507.76,
      "end": 1509.42
    },
    {
      "start": 1510.68,
      "end": 1512.26
    },
    {
      "start": 1513.66,
      "end": 1514.44
    },
    {
      "start": 1530.3,
      "end": 1531.2
    },
    {
      "start": 1535.9,
      "end": 1536.88
    },
    {
      "start": 1546.62,
      "end": 1548.14
    },
    {
      "start": 1550.34,
      "end": 1551.54
    },
    {
      "start": 1558.28,
      "end": 1559.38
    },
    {
      "start": 1563.7,
      "end": 1564.6
    },
    {
      "start": 1567.82,
      "end": 1568.8
    },
    {
      "start": 1580.98,
      "end": 1581.82
    },
    {
      "start": 1621.12,
      "end": 1625.12
    },
    {
      "start": 1626.2,
      "end": 1630.36
    },
    {
      "start": 1631.98,
      "end": 1633.22
    },
    {
      "start": 1635.9,
      "end": 1638.5
    },
    {
      "start": 1640.52,
      "end": 1642.76
    },
    {
      "start": 1686.84,
      "end": 1687.86
    },
    {
      "start": 1690.4,
      "end": 1691.36
    },
    {
      "start": 1695.72,
      "end": 1697.88
    },
    {
      "start": 1716.82,
      "end": 1717.64
    },
    {
      "start": 1719.02,
      "end": 1720.58
    },
    {
      "start": 1727.64,
      "end": 1728.8
    },
    {
      "start": 1755.68,
      "end": 1756.78
    },
    {
      "start": 1760.36,
      "end": 1762.28
    },
    {
      "start": 1765.14,
      "end": 1767.46
    },
    {
      "start": 1821.26,
      "end": 1822.22
    },
    {
      "start": 1850.8,
      "end": 1852.26
    },
    {
      "start": 1858.98,
      "end": 1860.18
    },
    {
      "start": 1861.56,
      "end": 1863.04
    },
    {
      "start": 1864.7,
      "end": 1865.52
    },
    {
      "start": 1874.4,
      "end": 1876.58
    },
    {
      "start": 1879.48,
      "end": 1880.5
    },
    {
      "start": 1898.94,
      "end": 1902.02
    },
    {
      "start": 1919.66,
      "end": 1920.66
    },
    {
      "start": 1925.28,
      "end": 1926.2
    },
    {
      "start": 1928.32,
      "end": 1929.22
    },
    {
      "start": 1935.32,
      "end": 1936.78
    },
    {
      "start": 1943.22,
      "end": 1944.0
    },
    {
      "start": 1946.08,
      "end": 1947.32
    },
    {
      "start": 1951.42,
      "end": 1953.02
    },
    {
      "start": 1958.8,
      "end": 1959.56
    },
    {
      "start": 1969.24,
      "end": 1970.2
    },
    {
      "start": 1980.1,
      "end": 1981.02
    },
    {
      "start": 1988.42,
      "end": 1990.5
    },
    {
      "start": 1993.38,
      "end": 1994.4
    },
    {
      "start": 2024.48,
      "end": 2025.58
    },
    {
      "start": 2027.22,
      "end": 2028.44
    },
    {
      "start": 2046.3,
      "end": 2048.26
    },
    {
      "start": 2050.42,
      "end": 2051.18
    },
    {
      "start": 2060.2,
      "end": 2061.0
    },
    {
      "start": 2065.48,
      "end": 2066.32
    },
    {
      "start": 2080.76,
      "end": 2081.52
    },
    {
      "start": 2100.3,
      "end": 2101.12
    },
    {
      "start": 2109.7,
      "end": 2110.88
    },
    {
      "start": 2120.58,
      "end": 2121.7
    },
    {
      "start": 2125.28,
      "end": 2126.32
    },
    {
      "start": 2127.88,
      "end": 2128.82
    },
    {
      "start": 2151.6,
      "end": 2153.72
    },
    {
      "start": 2158.66,
      "end": 2160.94
    },
    {
      "start": 2164.14,
      "end": 2165.5
    },
    {
      "start": 2166.8,
      "end": 2167.707
    }
  ]
}