{
  "id": "S1|pAVK Fr Gerhild mit Dr Dilara 18.11.2025.m4a",
  "name": "pAVK Fr Gerhild mit Dr Dilara 18.11.2025.m4a",
  "title": "pAVK Fr Gerhild mit Dr Dilara 18.11.2025.m4a",
  "src": "S1",
  "url": "https://archive.org/download/vorhofflimmern-bei-bekannter-khk-dr-oemer-dr-remzi-09.05.25/pAVK%20Fr%20Gerhild%20mit%20Dr%20Dilara%2018.11.2025.m4a",
  "duration": 2989.375,
  "sample_rate": 16000,
  "threshold": 0.015,
  "frame_ms": 20,
  "min_silence_ms": 900,
  "merge_gap_ms": 180,
  "keep_lead_ms": 60,
  "keep_tail_ms": 80,
  "min_skip_ms": 350,
  "max_skip_ms": 15000,
  "algo_version": "sm-v1",
  "analyzed_at": "2026-04-17T19:50:51Z",
  "segments": [
    {
      "start": 1.3,
      "end": 2.1
    },
    {
      "start": 13.32,
      "end": 14.16
    },
    {
      "start": 21.04,
      "end": 21.86
    },
    {
      "start": 25.54,
      "end": 27.32
    },
    {
      "start": 43.6,
      "end": 44.64
    },
    {
      "start": 52.5,
      "end": 54.36
    },
    {
      "start": 58.52,
      "end": 59.32
    },
    {
      "start": 59.82,
      "end": 60.6
    },
    {
      "start": 64.7,
      "end": 66.88
    },
    {
      "start": 71.1,
      "end": 71.94
    },
    {
      "start": 74.0,
      "end": 75.58
    },
    {
      "start": 77.2,
      "end": 78.06
    },
    {
      "start": 81.56,
      "end": 82.6
    },
    {
      "start": 101.98,
      "end": 102.94
    },
    {
      "start": 119.0,
      "end": 119.86
    },
    {
      "start": 151.56,
      "end": 152.48
    },
    {
      "start": 176.52,
      "end": 177.38
    },
    {
      "start": 177.76,
      "end": 178.76
    },
    {
      "start": 179.26,
      "end": 180.18
    },
    {
      "start": 191.86,
      "end": 193.84
    },
    {
      "start": 205.96,
      "end": 206.76
    },
    {
      "start": 213.28,
      "end": 214.64
    },
    {
      "start": 215.1,
      "end": 216.02
    },
    {
      "start": 233.02,
      "end": 236.72
    },
    {
      "start": 237.18,
      "end": 240.6
    },
    {
      "start": 241.98,
      "end": 242.82
    },
    {
      "start": 243.6,
      "end": 246.22
    },
    {
      "start": 264.5,
      "end": 267.24
    },
    {
      "start": 267.72,
      "end": 268.88
    },
    {
      "start": 269.7,
      "end": 270.72
    },
    {
      "start": 276.7,
      "end": 279.38
    },
    {
      "start": 288.22,
      "end": 289.6
    },
    {
      "start": 290.46,
      "end": 292.3
    },
    {
      "start": 296.56,
      "end": 297.42
    },
    {
      "start": 308.66,
      "end": 311.86
    },
    {
      "start": 337.42,
      "end": 341.34
    },
    {
      "start": 341.78,
      "end": 343.16
    },
    {
      "start": 351.36,
      "end": 352.74
    },
    {
      "start": 364.3,
      "end": 365.28
    },
    {
      "start": 367.02,
      "end": 368.06
    },
    {
      "start": 378.34,
      "end": 379.16
    },
    {
      "start": 380.2,
      "end": 381.0
    },
    {
      "start": 386.56,
      "end": 387.76
    },
    {
      "start": 391.56,
      "end": 395.12
    },
    {
      "start": 395.52,
      "end": 398.66
    },
    {
      "start": 399.06,
      "end": 399.9
    },
    {
      "start": 424.44,
      "end": 426.82
    },
    {
      "start": 432.16,
      "end": 433.12
    },
    {
      "start": 433.78,
      "end": 434.82
    },
    {
      "start": 444.08,
      "end": 444.84
    },
    {
      "start": 447.72,
      "end": 448.62
    },
    {
      "start": 462.26,
      "end": 463.06
    },
    {
      "start": 467.18,
      "end": 468.1
    },
    {
      "start": 472.1,
      "end": 474.22
    },
    {
      "start": 474.64,
      "end": 475.84
    },
    {
      "start": 485.5,
      "end": 486.58
    },
    {
      "start": 498.62,
      "end": 502.9
    },
    {
      "start": 510.68,
      "end": 511.5
    },
    {
      "start": 522.06,
      "end": 532.08
    },
    {
      "start": 542.26,
      "end": 543.44
    },
    {
      "start": 547.64,
      "end": 552.64
    },
    {
      "start": 553.04,
      "end": 558.44
    },
    {
      "start": 568.68,
      "end": 569.66
    },
    {
      "start": 596.14,
      "end": 597.18
    },
    {
      "start": 598.04,
      "end": 604.08
    },
    {
      "start": 618.28,
      "end": 619.3
    },
    {
      "start": 621.78,
      "end": 622.68
    },
    {
      "start": 623.34,
      "end": 625.3
    },
    {
      "start": 629.7,
      "end": 630.52
    },
    {
      "start": 631.78,
      "end": 632.8
    },
    {
      "start": 640.64,
      "end": 641.96
    },
    {
      "start": 651.1,
      "end": 651.94
    },
    {
      "start": 656.16,
      "end": 657.14
    },
    {
      "start": 681.52,
      "end": 684.54
    },
    {
      "start": 685.04,
      "end": 685.82
    },
    {
      "start": 686.62,
      "end": 689.14
    },
    {
      "start": 689.5,
      "end": 690.68
    },
    {
      "start": 693.28,
      "end": 694.62
    },
    {
      "start": 699.82,
      "end": 700.66
    },
    {
      "start": 711.18,
      "end": 712.4
    },
    {
      "start": 724.66,
      "end": 729.98
    },
    {
      "start": 771.84,
      "end": 772.74
    },
    {
      "start": 778.16,
      "end": 779.28
    },
    {
      "start": 780.64,
      "end": 781.56
    },
    {
      "start": 784.9,
      "end": 786.18
    },
    {
      "start": 796.78,
      "end": 797.66
    },
    {
      "start": 800.96,
      "end": 802.02
    },
    {
      "start": 807.7,
      "end": 809.06
    },
    {
      "start": 817.52,
      "end": 818.3
    },
    {
      "start": 820.36,
      "end": 823.68
    },
    {
      "start": 824.68,
      "end": 826.42
    },
    {
      "start": 837.08,
      "end": 837.98
    },
    {
      "start": 852.8,
      "end": 854.42
    },
    {
      "start": 854.78,
      "end": 856.26
    },
    {
      "start": 856.88,
      "end": 858.14
    },
    {
      "start": 862.0,
      "end": 863.22
    },
    {
      "start": 878.52,
      "end": 879.6
    },
    {
      "start": 889.48,
      "end": 890.84
    },
    {
      "start": 891.2,
      "end": 895.08
    },
    {
      "start": 904.16,
      "end": 905.56
    },
    {
      "start": 909.06,
      "end": 910.4
    },
    {
      "start": 910.76,
      "end": 914.26
    },
    {
      "start": 916.08,
      "end": 917.4
    },
    {
      "start": 919.32,
      "end": 920.6
    },
    {
      "start": 927.9,
      "end": 929.18
    },
    {
      "start": 932.26,
      "end": 933.92
    },
    {
      "start": 952.88,
      "end": 953.98
    },
    {
      "start": 959.32,
      "end": 960.76
    },
    {
      "start": 970.06,
      "end": 973.72
    },
    {
      "start": 975.6,
      "end": 976.52
    },
    {
      "start": 979.34,
      "end": 980.12
    },
    {
      "start": 988.04,
      "end": 988.82
    },
    {
      "start": 993.2,
      "end": 994.36
    },
    {
      "start": 1001.72,
      "end": 1006.02
    },
    {
      "start": 1007.62,
      "end": 1008.56
    },
    {
      "start": 1017.42,
      "end": 1018.68
    },
    {
      "start": 1019.7,
      "end": 1021.5
    },
    {
      "start": 1026.44,
      "end": 1027.5
    },
    {
      "start": 1043.18,
      "end": 1044.26
    },
    {
      "start": 1045.2,
      "end": 1046.16
    },
    {
      "start": 1061.46,
      "end": 1063.34
    },
    {
      "start": 1063.74,
      "end": 1064.66
    },
    {
      "start": 1066.04,
      "end": 1067.68
    },
    {
      "start": 1078.42,
      "end": 1079.26
    },
    {
      "start": 1084.2,
      "end": 1087.0
    },
    {
      "start": 1087.74,
      "end": 1094.6
    },
    {
      "start": 1102.32,
      "end": 1103.38
    },
    {
      "start": 1108.5,
      "end": 1109.3
    },
    {
      "start": 1109.66,
      "end": 1110.58
    },
    {
      "start": 1120.56,
      "end": 1121.6
    },
    {
      "start": 1135.6,
      "end": 1141.46
    },
    {
      "start": 1144.66,
      "end": 1145.68
    },
    {
      "start": 1148.44,
      "end": 1149.28
    },
    {
      "start": 1149.76,
      "end": 1150.72
    },
    {
      "start": 1154.98,
      "end": 1156.34
    },
    {
      "start": 1160.08,
      "end": 1160.92
    },
    {
      "start": 1162.48,
      "end": 1163.34
    },
    {
      "start": 1164.36,
      "end": 1165.52
    },
    {
      "start": 1166.28,
      "end": 1167.28
    },
    {
      "start": 1179.18,
      "end": 1180.56
    },
    {
      "start": 1183.14,
      "end": 1183.94
    },
    {
      "start": 1192.06,
      "end": 1192.94
    },
    {
      "start": 1195.9,
      "end": 1198.68
    },
    {
      "start": 1199.18,
      "end": 1201.18
    },
    {
      "start": 1210.02,
      "end": 1211.0
    },
    {
      "start": 1230.26,
      "end": 1231.12
    },
    {
      "start": 1239.44,
      "end": 1240.38
    },
    {
      "start": 1245.88,
      "end": 1246.78
    },
    {
      "start": 1260.34,
      "end": 1261.8
    },
    {
      "start": 1280.58,
      "end": 1283.74
    },
    {
      "start": 1284.26,
      "end": 1285.34
    },
    {
      "start": 1289.94,
      "end": 1291.64
    },
    {
      "start": 1293.0,
      "end": 1295.92
    },
    {
      "start": 1305.8,
      "end": 1306.6
    },
    {
      "start": 1323.72,
      "end": 1324.6
    },
    {
      "start": 1347.12,
      "end": 1348.46
    },
    {
      "start": 1376.3,
      "end": 1377.06
    },
    {
      "start": 1378.46,
      "end": 1384.94
    },
    {
      "start": 1388.18,
      "end": 1403.18
    },
    {
      "start": 1406.46,
      "end": 1407.72
    },
    {
      "start": 1409.38,
      "end": 1410.18
    },
    {
      "start": 1424.22,
      "end": 1439.22
    },
    {
      "start": 1489.86,
      "end": 1491.08
    },
    {
      "start": 1491.58,
      "end": 1494.14
    },
    {
      "start": 1494.62,
      "end": 1509.62
    },
    {
      "start": 1539.38,
      "end": 1541.0
    },
    {
      "start": 1544.16,
      "end": 1544.98
    },
    {
      "start": 1545.4,
      "end": 1546.22
    },
    {
      "start": 1546.64,
      "end": 1561.64
    },
    {
      "start": 1591.18,
      "end": 1594.42
    },
    {
      "start": 1600.94,
      "end": 1602.24
    },
    {
      "start": 1603.74,
      "end": 1606.86
    },
    {
      "start": 1608.12,
      "end": 1609.0
    },
    {
      "start": 1610.44,
      "end": 1611.4
    },
    {
      "start": 1625.14,
      "end": 1626.52
    },
    {
      "start": 1632.08,
      "end": 1633.06
    },
    {
      "start": 1658.04,
      "end": 1658.92
    },
    {
      "start": 1688.82,
      "end": 1689.9
    },
    {
      "start": 1696.66,
      "end": 1697.94
    },
    {
      "start": 1698.84,
      "end": 1700.1
    },
    {
      "start": 1701.24,
      "end": 1702.62
    },
    {
      "start": 1704.68,
      "end": 1707.64
    },
    {
      "start": 1708.52,
      "end": 1709.9
    },
    {
      "start": 1716.42,
      "end": 1717.22
    },
    {
      "start": 1725.7,
      "end": 1727.02
    },
    {
      "start": 1728.98,
      "end": 1730.26
    },
    {
      "start": 1748.26,
      "end": 1749.82
    },
    {
      "start": 1751.48,
      "end": 1753.68
    },
    {
      "start": 1755.66,
      "end": 1758.62
    },
    {
      "start": 1759.8,
      "end": 1760.58
    },
    {
      "start": 1772.9,
      "end": 1774.14
    },
    {
      "start": 1783.1,
      "end": 1783.92
    },
    {
      "start": 1785.42,
      "end": 1786.2
    },
    {
      "start": 1789.32,
      "end": 1790.12
    },
    {
      "start": 1794.02,
      "end": 1795.46
    },
    {
      "start": 1797.46,
      "end": 1798.74
    },
    {
      "start": 1810.34,
      "end": 1811.58
    },
    {
      "start": 1818.84,
      "end": 1819.64
    },
    {
      "start": 1827.2,
      "end": 1830.46
    },
    {
      "start": 1837.34,
      "end": 1838.18
    },
    {
      "start": 1850.4,
      "end": 1851.18
    },
    {
      "start": 1869.9,
      "end": 1871.92
    },
    {
      "start": 1877.44,
      "end": 1878.4
    },
    {
      "start": 1884.4,
      "end": 1885.38
    },
    {
      "start": 1906.52,
      "end": 1907.46
    },
    {
      "start": 1908.6,
      "end": 1910.06
    },
    {
      "start": 1913.88,
      "end": 1914.82
    },
    {
      "start": 1920.66,
      "end": 1921.66
    },
    {
      "start": 1942.54,
      "end": 1943.52
    },
    {
      "start": 1944.3,
      "end": 1946.64
    },
    {
      "start": 1950.92,
      "end": 1952.28
    },
    {
      "start": 1973.86,
      "end": 1974.88
    },
    {
      "start": 1984.44,
      "end": 1985.28
    },
    {
      "start": 1988.62,
      "end": 1989.44
    },
    {
      "start": 1993.9,
      "end": 1995.46
    },
    {
      "start": 2003.1,
      "end": 2003.98
    },
    {
      "start": 2010.02,
      "end": 2011.4
    },
    {
      "start": 2020.92,
      "end": 2022.16
    },
    {
      "start": 2031.68,
      "end": 2033.36
    },
    {
      "start": 2041.72,
      "end": 2042.96
    },
    {
      "start": 2046.96,
      "end": 2048.06
    },
    {
      "start": 2048.74,
      "end": 2049.92
    },
    {
      "start": 2061.32,
      "end": 2063.32
    },
    {
      "start": 2067.46,
      "end": 2068.32
    },
    {
      "start": 2071.16,
      "end": 2071.92
    },
    {
      "start": 2076.7,
      "end": 2078.0
    },
    {
      "start": 2085.84,
      "end": 2088.04
    },
    {
      "start": 2096.0,
      "end": 2096.8
    },
    {
      "start": 2113.04,
      "end": 2114.82
    },
    {
      "start": 2123.52,
      "end": 2124.72
    },
    {
      "start": 2140.88,
      "end": 2141.86
    },
    {
      "start": 2145.12,
      "end": 2146.14
    },
    {
      "start": 2147.06,
      "end": 2152.04
    },
    {
      "start": 2153.3,
      "end": 2154.88
    },
    {
      "start": 2159.02,
      "end": 2159.92
    },
    {
      "start": 2173.14,
      "end": 2173.98
    },
    {
      "start": 2207.68,
      "end": 2208.52
    },
    {
      "start": 2209.12,
      "end": 2209.98
    },
    {
      "start": 2211.46,
      "end": 2212.32
    },
    {
      "start": 2241.92,
      "end": 2243.04
    },
    {
      "start": 2244.42,
      "end": 2245.26
    },
    {
      "start": 2254.64,
      "end": 2255.44
    },
    {
      "start": 2267.9,
      "end": 2269.3
    },
    {
      "start": 2270.24,
      "end": 2271.1
    },
    {
      "start": 2272.62,
      "end": 2273.44
    },
    {
      "start": 2277.56,
      "end": 2278.42
    },
    {
      "start": 2280.42,
      "end": 2281.92
    },
    {
      "start": 2290.46,
      "end": 2291.44
    },
    {
      "start": 2292.88,
      "end": 2294.06
    },
    {
      "start": 2302.76,
      "end": 2303.96
    },
    {
      "start": 2312.26,
      "end": 2313.46
    },
    {
      "start": 2331.74,
      "end": 2334.1
    },
    {
      "start": 2337.1,
      "end": 2337.98
    },
    {
      "start": 2354.74,
      "end": 2355.8
    },
    {
      "start": 2365.78,
      "end": 2366.7
    },
    {
      "start": 2413.06,
      "end": 2413.82
    },
    {
      "start": 2420.42,
      "end": 2421.46
    },
    {
      "start": 2422.84,
      "end": 2423.86
    },
    {
      "start": 2429.18,
      "end": 2430.08
    },
    {
      "start": 2443.6,
      "end": 2444.62
    },
    {
      "start": 2452.44,
      "end": 2453.38
    },
    {
      "start": 2465.1,
      "end": 2466.2
    },
    {
      "start": 2466.8,
      "end": 2468.1
    },
    {
      "start": 2474.1,
      "end": 2475.04
    },
    {
      "start": 2486.34,
      "end": 2487.36
    },
    {
      "start": 2490.36,
      "end": 2491.26
    },
    {
      "start": 2492.46,
      "end": 2493.56
    },
    {
      "start": 2494.36,
      "end": 2495.2
    },
    {
      "start": 2522.38,
      "end": 2523.3
    },
    {
      "start": 2531.1,
      "end": 2532.4
    },
    {
      "start": 2545.94,
      "end": 2546.92
    },
    {
      "start": 2548.44,
      "end": 2552.38
    },
    {
      "start": 2576.52,
      "end": 2577.5
    },
    {
      "start": 2579.94,
      "end": 2580.84
    },
    {
      "start": 2582.06,
      "end": 2582.84
    },
    {
      "start": 2595.12,
      "end": 2596.6
    },
    {
      "start": 2603.04,
      "end": 2604.14
    },
    {
      "start": 2611.98,
      "end": 2613.18
    },
    {
      "start": 2614.2,
      "end": 2615.1
    },
    {
      "start": 2617.02,
      "end": 2618.06
    },
    {
      "start": 2619.1,
      "end": 2620.26
    },
    {
      "start": 2621.16,
      "end": 2622.2
    },
    {
      "start": 2630.7,
      "end": 2631.46
    },
    {
      "start": 2646.68,
      "end": 2648.4
    },
    {
      "start": 2657.32,
      "end": 2658.5
    },
    {
      "start": 2702.38,
      "end": 2703.62
    },
    {
      "start": 2719.0,
      "end": 2720.42
    },
    {
      "start": 2732.22,
      "end": 2733.32
    },
    {
      "start": 2736.3,
      "end": 2737.22
    },
    {
      "start": 2737.82,
      "end": 2739.08
    },
    {
      "start": 2751.86,
      "end": 2752.76
    },
    {
      "start": 2754.76,
      "end": 2756.06
    },
    {
      "start": 2759.68,
      "end": 2760.76
    },
    {
      "start": 2765.02,
      "end": 2766.24
    },
    {
      "start": 2778.9,
      "end": 2779.8
    },
    {
      "start": 2786.76,
      "end": 2787.52
    },
    {
      "start": 2790.04,
      "end": 2790.94
    },
    {
      "start": 2803.38,
      "end": 2804.46
    },
    {
      "start": 2807.32,
      "end": 2809.52
    },
    {
      "start": 2820.14,
      "end": 2830.36
    },
    {
      "start": 2831.14,
      "end": 2842.42
    },
    {
      "start": 2843.04,
      "end": 2849.14
    },
    {
      "start": 2851.1,
      "end": 2852.94
    },
    {
      "start": 2855.0,
      "end": 2856.74
    },
    {
      "start": 2858.02,
      "end": 2860.62
    },
    {
      "start": 2862.7,
      "end": 2865.66
    },
    {
      "start": 2868.78,
      "end": 2869.9
    },
    {
      "start": 2870.56,
      "end": 2872.98
    },
    {
      "start": 2874.36,
      "end": 2875.64
    },
    {
      "start": 2876.46,
      "end": 2877.96
    },
    {
      "start": 2879.94,
      "end": 2883.82
    },
    {
      "start": 2890.38,
      "end": 2899.1
    },
    {
      "start": 2917.28,
      "end": 2918.06
    },
    {
      "start": 2926.68,
      "end": 2929.4
    },
    {
      "start": 2953.5,
      "end": 2954.38
    },
    {
      "start": 2960.22,
      "end": 2960.98
    },
    {
      "start": 2984.74,
      "end": 2986.06
    }
  ]
}