{
  "id": "S1|akutes Koronarsyndrom (ACS) Fr Gerhild mit dr Dilara 08.01.2026.m4a",
  "name": "akutes Koronarsyndrom (ACS) Fr Gerhild mit dr Dilara 08.01.2026.m4a",
  "title": "akutes Koronarsyndrom (ACS) Fr Gerhild mit dr Dilara 08.01.2026.m4a",
  "src": "S1",
  "url": "https://archive.org/download/vorhofflimmern-bei-bekannter-khk-dr-oemer-dr-remzi-09.05.25/akutes%20Koronarsyndrom%20%28ACS%29%20Fr%20Gerhild%20mit%20dr%20Dilara%2008.01.2026.m4a",
  "duration": 3985.301,
  "sample_rate": 16000,
  "threshold": 0.01,
  "frame_ms": 30,
  "min_silence_ms": 1400,
  "merge_gap_ms": 320,
  "keep_lead_ms": 140,
  "keep_tail_ms": 180,
  "min_skip_ms": 900,
  "max_skip_ms": 12000,
  "algo_version": "sm-v2",
  "analyzed_at": "2026-04-26T22:00:55Z",
  "segments": [
    {
      "start": 1.07,
      "end": 3.0
    },
    {
      "start": 11.81,
      "end": 13.17
    },
    {
      "start": 50.63,
      "end": 52.38
    },
    {
      "start": 68.48,
      "end": 69.6
    },
    {
      "start": 164.96,
      "end": 166.35
    },
    {
      "start": 183.74,
      "end": 188.19
    },
    {
      "start": 223.16,
      "end": 224.88
    },
    {
      "start": 230.36,
      "end": 232.5
    },
    {
      "start": 245.09,
      "end": 246.39
    },
    {
      "start": 323.9,
      "end": 325.11
    },
    {
      "start": 340.04,
      "end": 341.37
    },
    {
      "start": 347.24,
      "end": 349.62
    },
    {
      "start": 350.42,
      "end": 354.09
    },
    {
      "start": 354.8,
      "end": 357.51
    },
    {
      "start": 366.77,
      "end": 371.64
    },
    {
      "start": 414.29,
      "end": 416.49
    },
    {
      "start": 418.16,
      "end": 420.42
    },
    {
      "start": 422.57,
      "end": 423.81
    },
    {
      "start": 446.9,
      "end": 448.29
    },
    {
      "start": 462.62,
      "end": 468.27
    },
    {
      "start": 482.63,
      "end": 484.71
    },
    {
      "start": 492.59,
      "end": 495.06
    },
    {
      "start": 498.32,
      "end": 502.56
    },
    {
      "start": 521.18,
      "end": 522.33
    },
    {
      "start": 527.9,
      "end": 530.4
    },
    {
      "start": 531.41,
      "end": 536.91
    },
    {
      "start": 557.27,
      "end": 562.26
    },
    {
      "start": 573.17,
      "end": 575.19
    },
    {
      "start": 595.88,
      "end": 597.18
    },
    {
      "start": 598.1,
      "end": 600.45
    },
    {
      "start": 601.16,
      "end": 602.55
    },
    {
      "start": 625.85,
      "end": 627.54
    },
    {
      "start": 641.42,
      "end": 642.72
    },
    {
      "start": 644.15,
      "end": 648.93
    },
    {
      "start": 652.79,
      "end": 654.06
    },
    {
      "start": 659.57,
      "end": 661.38
    },
    {
      "start": 665.75,
      "end": 666.9
    },
    {
      "start": 687.29,
      "end": 691.17
    },
    {
      "start": 729.62,
      "end": 731.1
    },
    {
      "start": 769.01,
      "end": 770.94
    },
    {
      "start": 771.83,
      "end": 773.91
    },
    {
      "start": 792.2,
      "end": 795.27
    },
    {
      "start": 795.98,
      "end": 797.22
    },
    {
      "start": 805.52,
      "end": 807.48
    },
    {
      "start": 877.01,
      "end": 878.46
    },
    {
      "start": 908.39,
      "end": 912.78
    },
    {
      "start": 918.17,
      "end": 919.26
    },
    {
      "start": 932.15,
      "end": 933.93
    },
    {
      "start": 955.13,
      "end": 957.3
    },
    {
      "start": 996.11,
      "end": 997.71
    },
    {
      "start": 999.26,
      "end": 1001.61
    },
    {
      "start": 1004.69,
      "end": 1016.69
    },
    {
      "start": 1030.55,
      "end": 1031.64
    },
    {
      "start": 1056.14,
      "end": 1057.29
    },
    {
      "start": 1067.33,
      "end": 1070.46
    },
    {
      "start": 1071.11,
      "end": 1072.2
    },
    {
      "start": 1082.18,
      "end": 1087.38
    },
    {
      "start": 1100.69,
      "end": 1102.44
    },
    {
      "start": 1115.24,
      "end": 1116.45
    },
    {
      "start": 1122.86,
      "end": 1125.09
    },
    {
      "start": 1127.87,
      "end": 1129.11
    },
    {
      "start": 1131.32,
      "end": 1135.32
    },
    {
      "start": 1165.31,
      "end": 1167.15
    },
    {
      "start": 1203.53,
      "end": 1204.71
    },
    {
      "start": 1205.72,
      "end": 1208.88
    },
    {
      "start": 1227.29,
      "end": 1228.74
    },
    {
      "start": 1232.27,
      "end": 1235.94
    },
    {
      "start": 1249.28,
      "end": 1250.49
    },
    {
      "start": 1254.38,
      "end": 1264.2
    },
    {
      "start": 1273.46,
      "end": 1278.27
    },
    {
      "start": 1285.28,
      "end": 1286.43
    },
    {
      "start": 1293.71,
      "end": 1299.6
    },
    {
      "start": 1330.04,
      "end": 1333.95
    },
    {
      "start": 1344.98,
      "end": 1346.16
    },
    {
      "start": 1399.73,
      "end": 1401.21
    },
    {
      "start": 1484.15,
      "end": 1486.02
    },
    {
      "start": 1494.59,
      "end": 1497.69
    },
    {
      "start": 1502.24,
      "end": 1504.08
    },
    {
      "start": 1512.98,
      "end": 1514.25
    },
    {
      "start": 1536.32,
      "end": 1538.01
    },
    {
      "start": 1581.53,
      "end": 1583.34
    },
    {
      "start": 1631.27,
      "end": 1634.58
    },
    {
      "start": 1648.28,
      "end": 1660.28
    },
    {
      "start": 1781.99,
      "end": 1787.64
    },
    {
      "start": 1842.44,
      "end": 1843.86
    },
    {
      "start": 1852.43,
      "end": 1855.05
    },
    {
      "start": 1870.52,
      "end": 1875.84
    },
    {
      "start": 1876.76,
      "end": 1878.69
    },
    {
      "start": 1882.28,
      "end": 1885.35
    },
    {
      "start": 1888.07,
      "end": 1889.79
    },
    {
      "start": 1927.37,
      "end": 1931.49
    },
    {
      "start": 1949.84,
      "end": 1951.89
    },
    {
      "start": 1953.92,
      "end": 1955.04
    },
    {
      "start": 1984.34,
      "end": 1985.88
    },
    {
      "start": 1987.64,
      "end": 1989.42
    },
    {
      "start": 2012.81,
      "end": 2015.04
    },
    {
      "start": 2034.32,
      "end": 2035.83
    },
    {
      "start": 2037.17,
      "end": 2038.41
    },
    {
      "start": 2050.88,
      "end": 2052.72
    },
    {
      "start": 2058.8,
      "end": 2060.37
    },
    {
      "start": 2064.38,
      "end": 2065.89
    },
    {
      "start": 2066.54,
      "end": 2077.32
    },
    {
      "start": 2081.21,
      "end": 2082.75
    },
    {
      "start": 2088.29,
      "end": 2094.48
    },
    {
      "start": 2121.83,
      "end": 2123.31
    },
    {
      "start": 2147.21,
      "end": 2150.1
    },
    {
      "start": 2153.42,
      "end": 2155.35
    },
    {
      "start": 2158.49,
      "end": 2160.84
    },
    {
      "start": 2170.19,
      "end": 2172.18
    },
    {
      "start": 2221.88,
      "end": 2223.63
    },
    {
      "start": 2224.82,
      "end": 2225.94
    },
    {
      "start": 2233.82,
      "end": 2235.18
    },
    {
      "start": 2252.03,
      "end": 2254.26
    },
    {
      "start": 2268.68,
      "end": 2270.67
    },
    {
      "start": 2272.55,
      "end": 2274.09
    },
    {
      "start": 2277.38,
      "end": 2279.16
    },
    {
      "start": 2282.84,
      "end": 2284.65
    },
    {
      "start": 2288.12,
      "end": 2289.93
    },
    {
      "start": 2317.7,
      "end": 2319.48
    },
    {
      "start": 2341.04,
      "end": 2342.64
    },
    {
      "start": 2353.25,
      "end": 2354.4
    },
    {
      "start": 2355.62,
      "end": 2357.19
    },
    {
      "start": 2419.7,
      "end": 2420.85
    },
    {
      "start": 2421.65,
      "end": 2424.96
    },
    {
      "start": 2429.03,
      "end": 2431.65
    },
    {
      "start": 2440.25,
      "end": 2441.46
    },
    {
      "start": 2461.55,
      "end": 2462.79
    },
    {
      "start": 2464.07,
      "end": 2466.93
    },
    {
      "start": 2473.7,
      "end": 2475.72
    },
    {
      "start": 2485.46,
      "end": 2486.58
    },
    {
      "start": 2503.88,
      "end": 2505.66
    },
    {
      "start": 2515.73,
      "end": 2517.21
    },
    {
      "start": 2523.2,
      "end": 2525.67
    },
    {
      "start": 2575.88,
      "end": 2577.93
    },
    {
      "start": 2584.37,
      "end": 2585.58
    },
    {
      "start": 2591.48,
      "end": 2592.75
    },
    {
      "start": 2613.65,
      "end": 2614.77
    },
    {
      "start": 2626.79,
      "end": 2628.12
    },
    {
      "start": 2655.14,
      "end": 2656.41
    },
    {
      "start": 2658.56,
      "end": 2660.43
    },
    {
      "start": 2673.62,
      "end": 2674.71
    },
    {
      "start": 2678.66,
      "end": 2679.81
    },
    {
      "start": 2687.15,
      "end": 2688.42
    },
    {
      "start": 2689.76,
      "end": 2691.72
    },
    {
      "start": 2694.2,
      "end": 2695.35
    },
    {
      "start": 2696.27,
      "end": 2700.93
    },
    {
      "start": 2702.0,
      "end": 2703.87
    },
    {
      "start": 2705.0,
      "end": 2708.37
    },
    {
      "start": 2712.83,
      "end": 2714.16
    },
    {
      "start": 2717.03,
      "end": 2721.0
    },
    {
      "start": 2725.49,
      "end": 2726.7
    },
    {
      "start": 2728.61,
      "end": 2729.82
    },
    {
      "start": 2731.31,
      "end": 2733.15
    },
    {
      "start": 2742.26,
      "end": 2743.47
    },
    {
      "start": 2748.14,
      "end": 2750.1
    },
    {
      "start": 2758.67,
      "end": 2760.03
    },
    {
      "start": 2771.78,
      "end": 2773.08
    },
    {
      "start": 2777.36,
      "end": 2778.75
    },
    {
      "start": 2784.53,
      "end": 2786.37
    },
    {
      "start": 2798.87,
      "end": 2801.04
    },
    {
      "start": 2818.37,
      "end": 2820.84
    },
    {
      "start": 2822.03,
      "end": 2828.58
    },
    {
      "start": 2837.75,
      "end": 2838.84
    },
    {
      "start": 2842.1,
      "end": 2854.1
    },
    {
      "start": 2878.88,
      "end": 2880.81
    },
    {
      "start": 2884.88,
      "end": 2886.15
    },
    {
      "start": 2889.56,
      "end": 2890.77
    },
    {
      "start": 2892.8,
      "end": 2895.09
    },
    {
      "start": 2902.37,
      "end": 2905.14
    },
    {
      "start": 2917.97,
      "end": 2926.47
    },
    {
      "start": 2930.99,
      "end": 2932.14
    },
    {
      "start": 2933.36,
      "end": 2945.36
    },
    {
      "start": 2973.29,
      "end": 2974.68
    },
    {
      "start": 3006.23,
      "end": 3007.71
    },
    {
      "start": 3067.55,
      "end": 3069.72
    },
    {
      "start": 3128.81,
      "end": 3130.53
    },
    {
      "start": 3161.78,
      "end": 3162.99
    },
    {
      "start": 3164.66,
      "end": 3165.75
    },
    {
      "start": 3185.03,
      "end": 3186.6
    },
    {
      "start": 3189.74,
      "end": 3191.28
    },
    {
      "start": 3196.55,
      "end": 3197.76
    },
    {
      "start": 3218.03,
      "end": 3221.55
    },
    {
      "start": 3231.89,
      "end": 3234.84
    },
    {
      "start": 3242.45,
      "end": 3246.63
    },
    {
      "start": 3251.75,
      "end": 3254.91
    },
    {
      "start": 3265.82,
      "end": 3267.12
    },
    {
      "start": 3268.76,
      "end": 3270.0
    },
    {
      "start": 3280.1,
      "end": 3281.31
    },
    {
      "start": 3353.93,
      "end": 3355.56
    },
    {
      "start": 3376.49,
      "end": 3377.58
    },
    {
      "start": 3471.11,
      "end": 3473.07
    },
    {
      "start": 3548.87,
      "end": 3550.41
    },
    {
      "start": 3551.33,
      "end": 3552.6
    },
    {
      "start": 3556.16,
      "end": 3558.0
    },
    {
      "start": 3561.77,
      "end": 3563.16
    },
    {
      "start": 3584.78,
      "end": 3586.32
    },
    {
      "start": 3659.72,
      "end": 3661.56
    },
    {
      "start": 3691.01,
      "end": 3692.67
    },
    {
      "start": 3695.42,
      "end": 3697.08
    },
    {
      "start": 3699.71,
      "end": 3702.15
    },
    {
      "start": 3723.92,
      "end": 3726.0
    },
    {
      "start": 3832.88,
      "end": 3834.54
    },
    {
      "start": 3869.33,
      "end": 3870.96
    },
    {
      "start": 3885.32,
      "end": 3886.41
    },
    {
      "start": 3936.47,
      "end": 3938.01
    }
  ]
}