{
  "id": "S1|Infektiöse Mononukleose Fr Gerhild mit Dr Alim 26.06.25.m4a",
  "name": "Infektiöse Mononukleose Fr Gerhild mit Dr Alim 26.06.25.m4a",
  "title": "Infektiöse Mononukleose Fr Gerhild mit Dr Alim 26.06.25.m4a",
  "src": "S1",
  "url": "https://archive.org/download/vorhofflimmern-bei-bekannter-khk-dr-oemer-dr-remzi-09.05.25/Infektio%CC%88se%20Mononukleose%20Fr%20Gerhild%20mit%20Dr%20Alim%2026.06.25.m4a",
  "duration": 2021.312,
  "sample_rate": 16000,
  "threshold": 0.01,
  "frame_ms": 30,
  "min_silence_ms": 1400,
  "merge_gap_ms": 320,
  "keep_lead_ms": 140,
  "keep_tail_ms": 180,
  "min_skip_ms": 900,
  "max_skip_ms": 12000,
  "algo_version": "sm-v2",
  "analyzed_at": "2026-04-26T22:26:10Z",
  "segments": [
    {
      "start": 0.14,
      "end": 1.59
    },
    {
      "start": 20.45,
      "end": 22.14
    },
    {
      "start": 32.96,
      "end": 34.11
    },
    {
      "start": 37.79,
      "end": 39.24
    },
    {
      "start": 42.83,
      "end": 43.95
    },
    {
      "start": 46.97,
      "end": 48.12
    },
    {
      "start": 54.86,
      "end": 57.15
    },
    {
      "start": 65.3,
      "end": 68.88
    },
    {
      "start": 73.07,
      "end": 74.7
    },
    {
      "start": 169.82,
      "end": 170.91
    },
    {
      "start": 204.2,
      "end": 205.59
    },
    {
      "start": 219.65,
      "end": 223.56
    },
    {
      "start": 233.15,
      "end": 234.63
    },
    {
      "start": 254.27,
      "end": 255.42
    },
    {
      "start": 262.85,
      "end": 265.14
    },
    {
      "start": 323.6,
      "end": 332.31
    },
    {
      "start": 334.19,
      "end": 335.31
    },
    {
      "start": 338.57,
      "end": 341.46
    },
    {
      "start": 344.75,
      "end": 346.02
    },
    {
      "start": 358.34,
      "end": 359.85
    },
    {
      "start": 372.98,
      "end": 377.37
    },
    {
      "start": 384.44,
      "end": 386.4
    },
    {
      "start": 391.07,
      "end": 392.34
    },
    {
      "start": 409.43,
      "end": 410.85
    },
    {
      "start": 413.54,
      "end": 415.14
    },
    {
      "start": 418.73,
      "end": 419.94
    },
    {
      "start": 424.19,
      "end": 426.42
    },
    {
      "start": 428.3,
      "end": 429.6
    },
    {
      "start": 460.58,
      "end": 462.06
    },
    {
      "start": 498.47,
      "end": 499.89
    },
    {
      "start": 500.57,
      "end": 502.2
    },
    {
      "start": 527.51,
      "end": 531.36
    },
    {
      "start": 546.62,
      "end": 549.09
    },
    {
      "start": 552.05,
      "end": 553.2
    },
    {
      "start": 610.19,
      "end": 611.46
    },
    {
      "start": 614.3,
      "end": 617.43
    },
    {
      "start": 621.38,
      "end": 622.47
    },
    {
      "start": 626.81,
      "end": 628.2
    },
    {
      "start": 637.61,
      "end": 639.3
    },
    {
      "start": 641.24,
      "end": 642.57
    },
    {
      "start": 661.61,
      "end": 663.09
    },
    {
      "start": 691.28,
      "end": 692.49
    },
    {
      "start": 693.62,
      "end": 695.73
    },
    {
      "start": 713.09,
      "end": 717.84
    },
    {
      "start": 737.42,
      "end": 741.63
    },
    {
      "start": 787.28,
      "end": 788.88
    },
    {
      "start": 793.07,
      "end": 795.0
    },
    {
      "start": 799.46,
      "end": 801.0
    },
    {
      "start": 811.1,
      "end": 813.06
    },
    {
      "start": 835.07,
      "end": 840.15
    },
    {
      "start": 888.95,
      "end": 890.34
    },
    {
      "start": 905.84,
      "end": 907.26
    },
    {
      "start": 910.85,
      "end": 913.14
    },
    {
      "start": 914.42,
      "end": 915.78
    },
    {
      "start": 958.43,
      "end": 960.42
    },
    {
      "start": 970.67,
      "end": 974.58
    },
    {
      "start": 982.37,
      "end": 983.58
    },
    {
      "start": 985.79,
      "end": 991.74
    },
    {
      "start": 1002.8,
      "end": 1014.8
    },
    {
      "start": 1027.49,
      "end": 1033.08
    },
    {
      "start": 1034.24,
      "end": 1035.96
    },
    {
      "start": 1037.63,
      "end": 1039.86
    },
    {
      "start": 1041.32,
      "end": 1043.31
    },
    {
      "start": 1061.66,
      "end": 1066.32
    },
    {
      "start": 1069.58,
      "end": 1071.27
    },
    {
      "start": 1149.32,
      "end": 1150.68
    },
    {
      "start": 1174.55,
      "end": 1175.64
    },
    {
      "start": 1232.63,
      "end": 1233.75
    },
    {
      "start": 1271.9,
      "end": 1273.17
    },
    {
      "start": 1372.88,
      "end": 1374.45
    },
    {
      "start": 1404.65,
      "end": 1406.67
    },
    {
      "start": 1540.88,
      "end": 1542.81
    },
    {
      "start": 1599.56,
      "end": 1601.16
    },
    {
      "start": 1618.37,
      "end": 1621.41
    },
    {
      "start": 1635.89,
      "end": 1637.43
    },
    {
      "start": 1679.3,
      "end": 1680.84
    },
    {
      "start": 1721.06,
      "end": 1722.36
    },
    {
      "start": 1844.3,
      "end": 1846.17
    },
    {
      "start": 1866.83,
      "end": 1868.04
    },
    {
      "start": 1877.75,
      "end": 1881.45
    },
    {
      "start": 1932.68,
      "end": 1933.77
    },
    {
      "start": 2017.46,
      "end": 2021.132
    }
  ]
}