{
  "id": "S2|HerzinsuffiZienZ Dr Heiko mit Dr Zehra Betül 12.03.2026.m4a",
  "name": "HerzinsuffiZienZ Dr Heiko mit Dr Zehra Betül 12.03.2026.m4a",
  "title": "HerzinsuffiZienZ Dr Heiko mit Dr Zehra Betül 12.03.2026.m4a",
  "src": "S2",
  "url": "https://archive.org/download/FSPneu/HerzinsuffiZienZ%20Dr%20Heiko%20mit%20Dr%20Zehra%20Bet%C3%BCl%2012.03.2026.m4a",
  "duration": 2312.875,
  "sample_rate": 16000,
  "threshold": 0.015,
  "frame_ms": 20,
  "min_silence_ms": 900,
  "merge_gap_ms": 180,
  "keep_lead_ms": 60,
  "keep_tail_ms": 80,
  "min_skip_ms": 350,
  "max_skip_ms": 15000,
  "algo_version": "sm-v1",
  "analyzed_at": "2026-04-17T06:29:50Z",
  "segments": [
    {
      "start": 0.98,
      "end": 4.52
    },
    {
      "start": 6.26,
      "end": 7.22
    },
    {
      "start": 23.3,
      "end": 24.06
    },
    {
      "start": 35.24,
      "end": 36.92
    },
    {
      "start": 38.6,
      "end": 41.14
    },
    {
      "start": 45.96,
      "end": 47.3
    },
    {
      "start": 50.74,
      "end": 51.64
    },
    {
      "start": 55.68,
      "end": 56.72
    },
    {
      "start": 66.1,
      "end": 67.0
    },
    {
      "start": 67.54,
      "end": 68.54
    },
    {
      "start": 70.42,
      "end": 71.2
    },
    {
      "start": 73.74,
      "end": 75.0
    },
    {
      "start": 79.04,
      "end": 79.86
    },
    {
      "start": 87.56,
      "end": 88.48
    },
    {
      "start": 91.56,
      "end": 92.8
    },
    {
      "start": 104.1,
      "end": 106.02
    },
    {
      "start": 124.46,
      "end": 125.52
    },
    {
      "start": 143.02,
      "end": 146.72
    },
    {
      "start": 162.0,
      "end": 164.12
    },
    {
      "start": 172.26,
      "end": 174.14
    },
    {
      "start": 174.54,
      "end": 177.28
    },
    {
      "start": 179.7,
      "end": 181.26
    },
    {
      "start": 182.64,
      "end": 183.7
    },
    {
      "start": 184.94,
      "end": 186.16
    },
    {
      "start": 186.84,
      "end": 188.44
    },
    {
      "start": 201.78,
      "end": 203.4
    },
    {
      "start": 223.94,
      "end": 224.94
    },
    {
      "start": 231.62,
      "end": 232.76
    },
    {
      "start": 235.22,
      "end": 236.84
    },
    {
      "start": 243.2,
      "end": 244.94
    },
    {
      "start": 252.9,
      "end": 254.1
    },
    {
      "start": 259.9,
      "end": 261.6
    },
    {
      "start": 263.28,
      "end": 264.52
    },
    {
      "start": 269.9,
      "end": 272.32
    },
    {
      "start": 281.4,
      "end": 282.38
    },
    {
      "start": 284.96,
      "end": 287.16
    },
    {
      "start": 290.36,
      "end": 291.18
    },
    {
      "start": 291.56,
      "end": 292.96
    },
    {
      "start": 296.3,
      "end": 298.22
    },
    {
      "start": 301.4,
      "end": 303.96
    },
    {
      "start": 310.98,
      "end": 311.76
    },
    {
      "start": 318.34,
      "end": 319.12
    },
    {
      "start": 340.16,
      "end": 341.7
    },
    {
      "start": 344.04,
      "end": 344.86
    },
    {
      "start": 345.4,
      "end": 346.46
    },
    {
      "start": 349.08,
      "end": 350.2
    },
    {
      "start": 360.52,
      "end": 361.66
    },
    {
      "start": 362.26,
      "end": 363.64
    },
    {
      "start": 377.52,
      "end": 379.48
    },
    {
      "start": 389.06,
      "end": 390.56
    },
    {
      "start": 399.38,
      "end": 400.54
    },
    {
      "start": 406.46,
      "end": 407.38
    },
    {
      "start": 422.28,
      "end": 423.34
    },
    {
      "start": 426.02,
      "end": 432.2
    },
    {
      "start": 435.82,
      "end": 441.98
    },
    {
      "start": 444.16,
      "end": 445.26
    },
    {
      "start": 446.12,
      "end": 451.48
    },
    {
      "start": 455.8,
      "end": 459.66
    },
    {
      "start": 460.9,
      "end": 462.36
    },
    {
      "start": 480.82,
      "end": 482.08
    },
    {
      "start": 487.16,
      "end": 488.18
    },
    {
      "start": 493.68,
      "end": 494.58
    },
    {
      "start": 510.12,
      "end": 511.44
    },
    {
      "start": 512.12,
      "end": 514.0
    },
    {
      "start": 526.16,
      "end": 527.96
    },
    {
      "start": 528.28,
      "end": 535.48
    },
    {
      "start": 560.82,
      "end": 562.8
    },
    {
      "start": 563.26,
      "end": 566.46
    },
    {
      "start": 575.7,
      "end": 577.56
    },
    {
      "start": 590.24,
      "end": 591.86
    },
    {
      "start": 594.16,
      "end": 594.94
    },
    {
      "start": 597.02,
      "end": 598.1
    },
    {
      "start": 599.38,
      "end": 600.36
    },
    {
      "start": 602.16,
      "end": 603.48
    },
    {
      "start": 614.8,
      "end": 615.72
    },
    {
      "start": 629.8,
      "end": 633.36
    },
    {
      "start": 640.08,
      "end": 643.96
    },
    {
      "start": 646.78,
      "end": 654.04
    },
    {
      "start": 657.3,
      "end": 658.38
    },
    {
      "start": 675.04,
      "end": 683.46
    },
    {
      "start": 687.02,
      "end": 687.92
    },
    {
      "start": 689.86,
      "end": 691.04
    },
    {
      "start": 694.08,
      "end": 696.28
    },
    {
      "start": 702.8,
      "end": 703.6
    },
    {
      "start": 705.62,
      "end": 707.04
    },
    {
      "start": 708.2,
      "end": 709.02
    },
    {
      "start": 709.66,
      "end": 711.4
    },
    {
      "start": 712.3,
      "end": 714.66
    },
    {
      "start": 722.28,
      "end": 724.3
    },
    {
      "start": 730.42,
      "end": 731.46
    },
    {
      "start": 745.7,
      "end": 746.6
    },
    {
      "start": 751.2,
      "end": 752.54
    },
    {
      "start": 759.6,
      "end": 763.02
    },
    {
      "start": 763.82,
      "end": 768.9
    },
    {
      "start": 775.48,
      "end": 777.84
    },
    {
      "start": 784.26,
      "end": 786.2
    },
    {
      "start": 786.78,
      "end": 787.62
    },
    {
      "start": 789.06,
      "end": 791.26
    },
    {
      "start": 791.8,
      "end": 796.12
    },
    {
      "start": 796.48,
      "end": 798.14
    },
    {
      "start": 798.9,
      "end": 799.86
    },
    {
      "start": 813.76,
      "end": 815.06
    },
    {
      "start": 821.86,
      "end": 823.06
    },
    {
      "start": 825.08,
      "end": 828.22
    },
    {
      "start": 831.08,
      "end": 833.22
    },
    {
      "start": 834.82,
      "end": 836.0
    },
    {
      "start": 840.36,
      "end": 841.88
    },
    {
      "start": 845.58,
      "end": 847.26
    },
    {
      "start": 859.22,
      "end": 860.04
    },
    {
      "start": 865.8,
      "end": 869.38
    },
    {
      "start": 892.62,
      "end": 893.48
    },
    {
      "start": 896.14,
      "end": 899.36
    },
    {
      "start": 906.36,
      "end": 907.84
    },
    {
      "start": 908.24,
      "end": 909.08
    },
    {
      "start": 910.06,
      "end": 911.42
    },
    {
      "start": 914.4,
      "end": 915.32
    },
    {
      "start": 925.68,
      "end": 926.66
    },
    {
      "start": 927.12,
      "end": 928.42
    },
    {
      "start": 940.92,
      "end": 941.78
    },
    {
      "start": 942.94,
      "end": 944.94
    },
    {
      "start": 945.36,
      "end": 953.22
    },
    {
      "start": 955.0,
      "end": 956.1
    },
    {
      "start": 958.6,
      "end": 959.58
    },
    {
      "start": 967.62,
      "end": 969.7
    },
    {
      "start": 970.56,
      "end": 972.78
    },
    {
      "start": 983.06,
      "end": 983.84
    },
    {
      "start": 1003.4,
      "end": 1004.82
    },
    {
      "start": 1017.68,
      "end": 1021.24
    },
    {
      "start": 1027.92,
      "end": 1029.98
    },
    {
      "start": 1082.44,
      "end": 1083.86
    },
    {
      "start": 1090.9,
      "end": 1091.96
    },
    {
      "start": 1107.4,
      "end": 1108.46
    },
    {
      "start": 1110.08,
      "end": 1114.36
    },
    {
      "start": 1115.82,
      "end": 1117.24
    },
    {
      "start": 1128.06,
      "end": 1128.94
    },
    {
      "start": 1134.74,
      "end": 1135.54
    },
    {
      "start": 1135.88,
      "end": 1136.84
    },
    {
      "start": 1161.64,
      "end": 1162.64
    },
    {
      "start": 1172.88,
      "end": 1178.94
    },
    {
      "start": 1182.92,
      "end": 1184.2
    },
    {
      "start": 1194.46,
      "end": 1200.24
    },
    {
      "start": 1205.42,
      "end": 1207.42
    },
    {
      "start": 1215.04,
      "end": 1227.14
    },
    {
      "start": 1230.12,
      "end": 1230.94
    },
    {
      "start": 1264.54,
      "end": 1269.12
    },
    {
      "start": 1269.6,
      "end": 1273.6
    },
    {
      "start": 1274.16,
      "end": 1275.0
    },
    {
      "start": 1275.48,
      "end": 1277.46
    },
    {
      "start": 1278.06,
      "end": 1279.48
    },
    {
      "start": 1282.36,
      "end": 1283.86
    },
    {
      "start": 1286.18,
      "end": 1287.2
    },
    {
      "start": 1312.54,
      "end": 1313.54
    },
    {
      "start": 1324.5,
      "end": 1326.1
    },
    {
      "start": 1345.1,
      "end": 1346.12
    },
    {
      "start": 1357.06,
      "end": 1357.82
    },
    {
      "start": 1363.2,
      "end": 1364.28
    },
    {
      "start": 1365.36,
      "end": 1367.36
    },
    {
      "start": 1367.7,
      "end": 1368.48
    },
    {
      "start": 1395.3,
      "end": 1400.42
    },
    {
      "start": 1419.12,
      "end": 1420.48
    },
    {
      "start": 1441.54,
      "end": 1442.74
    },
    {
      "start": 1456.7,
      "end": 1458.64
    },
    {
      "start": 1459.56,
      "end": 1461.16
    },
    {
      "start": 1481.54,
      "end": 1482.4
    },
    {
      "start": 1484.36,
      "end": 1485.28
    },
    {
      "start": 1492.28,
      "end": 1493.36
    },
    {
      "start": 1574.1,
      "end": 1574.96
    },
    {
      "start": 1583.7,
      "end": 1584.9
    },
    {
      "start": 1614.06,
      "end": 1614.98
    },
    {
      "start": 1621.84,
      "end": 1622.72
    },
    {
      "start": 1632.96,
      "end": 1634.12
    },
    {
      "start": 1684.54,
      "end": 1685.44
    },
    {
      "start": 1703.68,
      "end": 1704.66
    },
    {
      "start": 1713.5,
      "end": 1714.62
    },
    {
      "start": 1720.48,
      "end": 1721.5
    },
    {
      "start": 1749.12,
      "end": 1750.22
    },
    {
      "start": 1755.6,
      "end": 1756.42
    },
    {
      "start": 1772.6,
      "end": 1774.36
    },
    {
      "start": 1774.94,
      "end": 1775.74
    },
    {
      "start": 1786.64,
      "end": 1787.8
    },
    {
      "start": 1792.08,
      "end": 1792.92
    },
    {
      "start": 1797.74,
      "end": 1799.74
    },
    {
      "start": 1821.42,
      "end": 1823.12
    },
    {
      "start": 1829.06,
      "end": 1829.96
    },
    {
      "start": 1837.62,
      "end": 1838.46
    },
    {
      "start": 1839.6,
      "end": 1841.0
    },
    {
      "start": 1852.96,
      "end": 1854.16
    },
    {
      "start": 1857.78,
      "end": 1859.88
    },
    {
      "start": 1861.38,
      "end": 1863.04
    },
    {
      "start": 1871.42,
      "end": 1872.18
    },
    {
      "start": 1872.74,
      "end": 1873.54
    },
    {
      "start": 1908.66,
      "end": 1910.18
    },
    {
      "start": 1918.68,
      "end": 1919.84
    },
    {
      "start": 1934.96,
      "end": 1935.82
    },
    {
      "start": 1942.08,
      "end": 1943.92
    },
    {
      "start": 1945.86,
      "end": 1947.16
    },
    {
      "start": 1955.06,
      "end": 1955.82
    },
    {
      "start": 1956.78,
      "end": 1957.58
    },
    {
      "start": 1965.14,
      "end": 1966.66
    },
    {
      "start": 1967.74,
      "end": 1968.8
    },
    {
      "start": 1982.1,
      "end": 1983.92
    },
    {
      "start": 1994.6,
      "end": 1995.5
    },
    {
      "start": 2011.94,
      "end": 2012.84
    },
    {
      "start": 2023.32,
      "end": 2024.08
    },
    {
      "start": 2055.36,
      "end": 2056.24
    },
    {
      "start": 2082.66,
      "end": 2083.42
    },
    {
      "start": 2094.76,
      "end": 2095.54
    },
    {
      "start": 2102.06,
      "end": 2102.86
    },
    {
      "start": 2155.92,
      "end": 2156.7
    },
    {
      "start": 2185.68,
      "end": 2186.5
    },
    {
      "start": 2217.98,
      "end": 2218.96
    },
    {
      "start": 2223.36,
      "end": 2224.24
    },
    {
      "start": 2225.52,
      "end": 2226.56
    },
    {
      "start": 2231.82,
      "end": 2233.02
    },
    {
      "start": 2244.98,
      "end": 2246.38
    },
    {
      "start": 2303.6,
      "end": 2304.36
    },
    {
      "start": 2305.08,
      "end": 2306.66
    }
  ]
}