{
  "id": "S2|Pyelonephritis Dr.Ömer mit Dr.Sevilay 10.04.2026.m4a",
  "name": "Pyelonephritis Dr.Ömer mit Dr.Sevilay 10.04.2026.m4a",
  "title": "Pyelonephritis Dr.Ömer mit Dr.Sevilay 10.04.2026.m4a",
  "src": "S2",
  "url": "https://archive.org/download/FSPneu/Pyelonephritis%20Dr.%C3%96mer%20mit%20Dr.Sevilay%2010.04.2026.m4a",
  "duration": 1992.085,
  "sample_rate": 16000,
  "threshold": 0.01,
  "frame_ms": 30,
  "min_silence_ms": 1400,
  "merge_gap_ms": 320,
  "keep_lead_ms": 140,
  "keep_tail_ms": 180,
  "min_skip_ms": 900,
  "max_skip_ms": 12000,
  "algo_version": "sm-v2",
  "analyzed_at": "2026-04-26T12:14:11Z",
  "segments": [
    {
      "start": 3.23,
      "end": 4.38
    },
    {
      "start": 45.38,
      "end": 47.25
    },
    {
      "start": 82.85,
      "end": 84.21
    },
    {
      "start": 87.02,
      "end": 88.29
    },
    {
      "start": 93.65,
      "end": 100.05
    },
    {
      "start": 119.51,
      "end": 122.55
    },
    {
      "start": 175.58,
      "end": 177.18
    },
    {
      "start": 215.9,
      "end": 218.25
    },
    {
      "start": 254.09,
      "end": 258.27
    },
    {
      "start": 298.67,
      "end": 300.15
    },
    {
      "start": 305.0,
      "end": 309.78
    },
    {
      "start": 314.21,
      "end": 317.31
    },
    {
      "start": 324.47,
      "end": 326.19
    },
    {
      "start": 341.09,
      "end": 343.83
    },
    {
      "start": 352.13,
      "end": 354.27
    },
    {
      "start": 371.54,
      "end": 375.81
    },
    {
      "start": 388.67,
      "end": 391.8
    },
    {
      "start": 433.34,
      "end": 437.37
    },
    {
      "start": 440.54,
      "end": 441.72
    },
    {
      "start": 443.12,
      "end": 444.27
    },
    {
      "start": 451.25,
      "end": 457.59
    },
    {
      "start": 466.97,
      "end": 468.33
    },
    {
      "start": 475.7,
      "end": 476.79
    },
    {
      "start": 485.96,
      "end": 488.25
    },
    {
      "start": 489.11,
      "end": 493.05
    },
    {
      "start": 501.26,
      "end": 502.83
    },
    {
      "start": 530.51,
      "end": 534.99
    },
    {
      "start": 564.11,
      "end": 565.77
    },
    {
      "start": 589.73,
      "end": 591.69
    },
    {
      "start": 598.25,
      "end": 602.25
    },
    {
      "start": 607.43,
      "end": 609.12
    },
    {
      "start": 624.89,
      "end": 631.11
    },
    {
      "start": 635.75,
      "end": 636.96
    },
    {
      "start": 649.79,
      "end": 650.97
    },
    {
      "start": 658.49,
      "end": 662.94
    },
    {
      "start": 675.56,
      "end": 677.67
    },
    {
      "start": 715.4,
      "end": 719.7
    },
    {
      "start": 726.38,
      "end": 727.5
    },
    {
      "start": 733.61,
      "end": 734.91
    },
    {
      "start": 742.61,
      "end": 745.14
    },
    {
      "start": 759.29,
      "end": 762.99
    },
    {
      "start": 771.38,
      "end": 773.7
    },
    {
      "start": 816.89,
      "end": 818.1
    },
    {
      "start": 819.02,
      "end": 820.47
    },
    {
      "start": 825.74,
      "end": 826.98
    },
    {
      "start": 830.09,
      "end": 834.0
    },
    {
      "start": 841.4,
      "end": 844.86
    },
    {
      "start": 854.15,
      "end": 855.63
    },
    {
      "start": 884.81,
      "end": 888.06
    },
    {
      "start": 930.89,
      "end": 932.13
    },
    {
      "start": 940.4,
      "end": 941.61
    },
    {
      "start": 982.55,
      "end": 984.42
    },
    {
      "start": 990.53,
      "end": 992.76
    },
    {
      "start": 1005.44,
      "end": 1007.7
    },
    {
      "start": 1008.47,
      "end": 1010.64
    },
    {
      "start": 1042.1,
      "end": 1043.58
    },
    {
      "start": 1047.32,
      "end": 1049.76
    },
    {
      "start": 1059.2,
      "end": 1061.61
    },
    {
      "start": 1103.93,
      "end": 1105.11
    },
    {
      "start": 1129.76,
      "end": 1132.86
    },
    {
      "start": 1136.78,
      "end": 1138.98
    },
    {
      "start": 1161.2,
      "end": 1165.68
    },
    {
      "start": 1170.47,
      "end": 1173.27
    },
    {
      "start": 1177.73,
      "end": 1178.82
    },
    {
      "start": 1190.81,
      "end": 1193.31
    },
    {
      "start": 1197.17,
      "end": 1198.56
    },
    {
      "start": 1207.19,
      "end": 1212.42
    },
    {
      "start": 1215.32,
      "end": 1219.05
    },
    {
      "start": 1220.03,
      "end": 1222.86
    },
    {
      "start": 1263.23,
      "end": 1264.32
    },
    {
      "start": 1276.01,
      "end": 1277.28
    },
    {
      "start": 1344.77,
      "end": 1347.33
    },
    {
      "start": 1352.66,
      "end": 1354.83
    },
    {
      "start": 1365.35,
      "end": 1366.71
    },
    {
      "start": 1401.17,
      "end": 1402.86
    },
    {
      "start": 1409.42,
      "end": 1410.72
    },
    {
      "start": 1415.42,
      "end": 1416.93
    },
    {
      "start": 1435.31,
      "end": 1436.52
    },
    {
      "start": 1477.58,
      "end": 1478.94
    },
    {
      "start": 1481.06,
      "end": 1482.78
    },
    {
      "start": 1510.88,
      "end": 1512.45
    },
    {
      "start": 1534.13,
      "end": 1535.25
    },
    {
      "start": 1567.13,
      "end": 1568.37
    },
    {
      "start": 1572.83,
      "end": 1574.52
    },
    {
      "start": 1575.26,
      "end": 1581.15
    },
    {
      "start": 1595.96,
      "end": 1600.02
    },
    {
      "start": 1601.12,
      "end": 1604.88
    },
    {
      "start": 1643.84,
      "end": 1645.2
    },
    {
      "start": 1687.28,
      "end": 1690.44
    },
    {
      "start": 1691.81,
      "end": 1693.14
    },
    {
      "start": 1699.01,
      "end": 1701.57
    },
    {
      "start": 1707.11,
      "end": 1708.86
    },
    {
      "start": 1729.97,
      "end": 1732.74
    },
    {
      "start": 1743.59,
      "end": 1744.98
    },
    {
      "start": 1753.52,
      "end": 1757.61
    },
    {
      "start": 1763.12,
      "end": 1765.5
    },
    {
      "start": 1801.55,
      "end": 1803.0
    },
    {
      "start": 1866.23,
      "end": 1868.01
    },
    {
      "start": 1877.69,
      "end": 1878.9
    },
    {
      "start": 1906.79,
      "end": 1908.15
    },
    {
      "start": 1909.04,
      "end": 1910.67
    },
    {
      "start": 1920.5,
      "end": 1921.86
    },
    {
      "start": 1947.98,
      "end": 1949.49
    }
  ]
}